piercrop/__init__.py
piercrop/pcode_tools.py
piercrop/pixval_tools.py
piercrop/plant_info_tools.py
piercrop-0.1.0.0.0.dist-info/LICENSE
piercrop-0.1.0.0.0.dist-info/METADATA
piercrop-0.1.0.0.0.dist-info/WHEEL
piercrop-0.1.0.0.0.dist-info/top_level.txt
piercrop-0.1.0.0.0.dist-info/RECORD
