Metadata-Version: 2.1
Name: piercrop
Version: 0.1.0.0.0
Summary: A PIER's crop insurance project package
Home-page: https://github.com/surasakcho/piercrop
Author: Surasak Choedpasuporn
Author-email: surasak.cho@gmail.com
License: UNKNOWN
Platform: UNKNOWN
Classifier: Programming Language :: Python :: 3
Classifier: License :: OSI Approved :: MIT License
Classifier: Operating System :: OS Independent
Requires-Python: >=3.6
License-File: LICENSE
